VorGemeinde/Gemeinde.py
VorGemeinde/__init__.py
VorGemeinde/package_data.dat
VorGemeinde-0.2.0.data/data/my_data/data_file
VorGemeinde-0.2.0.dist-info/LICENSE.txt
VorGemeinde-0.2.0.dist-info/METADATA
VorGemeinde-0.2.0.dist-info/WHEEL
VorGemeinde-0.2.0.dist-info/entry_points.txt
VorGemeinde-0.2.0.dist-info/top_level.txt
VorGemeinde-0.2.0.dist-info/RECORD
